{
  "last_updated": "2025-11-28T09:39:54.140204-08:00",
  "special": [
    {
      "studio": "Turf",
      "name": "COMMUNITY CLASS: meta",
      "booking_start_date": "2025-11-27 08:15",
      "location": "KITS - Vancouver",
      "start_date": "2025-12-04",
      "start_time": "08:15",
      "available_spot_count": 23,
      "capacity": 32
    },
    {
      "studio": "Turf",
      "name": "COMMUNITY CLASS: meta",
      "booking_start_date": "2025-12-04 08:15",
      "location": "KITS - Vancouver",
      "start_date": "2025-12-11",
      "start_time": "08:15",
      "available_spot_count": 32,
      "capacity": 32
    },
    {
      "studio": "Turf",
      "name": "COMMUNITY CLASS: meta",
      "booking_start_date": "2025-12-11 08:15",
      "location": "KITS - Vancouver",
      "start_date": "2025-12-18",
      "start_time": "08:15",
      "available_spot_count": 32,
      "capacity": 32
    },
    {
      "studio": "Turf",
      "name": "COMMUNITY CLASS: meta",
      "booking_start_date": "2025-12-18 08:15",
      "location": "KITS - Vancouver",
      "start_date": "2025-12-25",
      "start_time": "08:15",
      "available_spot_count": 32,
      "capacity": 32
    },
    {
      "studio": "Turf",
      "name": "COMMUNITY CLASS: meta",
      "booking_start_date": "2025-12-25 08:15",
      "location": "KITS - Vancouver",
      "start_date": "2026-01-01",
      "start_time": "08:15",
      "available_spot_count": 32,
      "capacity": 32
    },
    {
      "studio": "Turf",
      "name": "COMMUNITY CLASS: meta",
      "booking_start_date": "2026-01-01 08:15",
      "location": "KITS - Vancouver",
      "start_date": "2026-01-08",
      "start_time": "08:15",
      "available_spot_count": 32,
      "capacity": 32
    }
  ],
  "sponsored": [
    {
      "studio": "Lagree West",
      "name": "Happy Hour Megaformer x Fred Again",
      "booking_start_date": "2025-11-21 00:00",
      "location": "Kitsilano",
      "start_date": "2025-11-28",
      "start_time": "14:30",
      "available_spot_count": 2,
      "capacity": 16
    },
    {
      "studio": "Lagree West",
      "name": "Megaformer x 10YR with OG Katie McKenzie",
      "booking_start_date": "2025-10-29 15:15",
      "location": "Yaletown",
      "start_date": "2025-11-28",
      "start_time": "15:15",
      "available_spot_count": 0,
      "capacity": 20
    },
    {
      "studio": "Lagree West",
      "name": "Megaformer x Fred Again",
      "booking_start_date": "2025-11-21 00:00",
      "location": "Kitsilano",
      "start_date": "2025-11-28",
      "start_time": "15:30",
      "available_spot_count": 2,
      "capacity": 16
    },
    {
      "studio": "Lagree West",
      "name": "Mega Cardio Xpress- Arms/Abs+Tread x Fred Again",
      "booking_start_date": "2025-11-21 00:00",
      "location": "Kitsilano",
      "start_date": "2025-11-28",
      "start_time": "16:30",
      "available_spot_count": 11,
      "capacity": 26
    },
    {
      "studio": "Lagree West",
      "name": "Happy Hour Megaformer x Fred Again",
      "booking_start_date": "2025-11-21 00:00",
      "location": "Kitsilano",
      "start_date": "2025-11-28",
      "start_time": "17:30",
      "available_spot_count": 2,
      "capacity": 16
    },
    {
      "studio": "Lagree West",
      "name": "Sweat for a Cause/By Donation",
      "booking_start_date": "2025-11-04 13:15",
      "location": "Kitsilano",
      "start_date": "2025-12-04",
      "start_time": "13:15",
      "available_spot_count": 13,
      "capacity": 16
    },
    {
      "studio": "Lagree West",
      "name": "Sweat for a Cause/By Donation",
      "booking_start_date": "2025-11-11 09:15",
      "location": "Yaletown",
      "start_date": "2025-12-11",
      "start_time": "09:15",
      "available_spot_count": 8,
      "capacity": 20
    },
    {
      "studio": "Lagree West",
      "name": "Sweat for a Cause/By Donation",
      "booking_start_date": "2025-11-19 14:15",
      "location": "Main St",
      "start_date": "2025-12-19",
      "start_time": "14:15",
      "available_spot_count": 12,
      "capacity": 14
    },
    {
      "studio": "Jaybird",
      "name": "The Burn: Sweat for the DTES Women's Centre",
      "booking_start_date": "2025-10-30 13:45",
      "location": "Kingsway",
      "start_date": "2025-11-29",
      "start_time": "13:45",
      "available_spot_count": 8,
      "capacity": 45
    },
    {
      "studio": "Jaybird",
      "name": "Sweat for a Cause | The Build",
      "booking_start_date": "2025-11-25 00:00",
      "location": "Kingsway",
      "start_date": "2025-12-02",
      "start_time": "06:10",
      "available_spot_count": 36,
      "capacity": 45
    },
    {
      "studio": "Lagree Studio",
      "name": "Club Lagree x Full Body W/Headsets x Sahajan",
      "booking_start_date": "2025-11-21 09:00",
      "location": "Vancouver",
      "start_date": "2025-11-28",
      "start_time": "09:00",
      "available_spot_count": 1,
      "capacity": 12
    },
    {
      "studio": "Lagree Studio",
      "name": "*Daytime Deal* Full Body Workout With Headsets",
      "booking_start_date": "2025-11-21 10:00",
      "location": "Vancouver",
      "start_date": "2025-11-28",
      "start_time": "10:00",
      "available_spot_count": 8,
      "capacity": 12
    },
    {
      "studio": "Lagree Studio",
      "name": "*Daytime Deal* Full Body Workout With Headsets",
      "booking_start_date": "2025-11-21 13:00",
      "location": "Vancouver",
      "start_date": "2025-11-28",
      "start_time": "13:00",
      "available_spot_count": 9,
      "capacity": 12
    },
    {
      "studio": "Ritual",
      "name": "Vinyasa Slow Flow Yoga + Sound",
      "booking_start_date": "2025-11-18 08:00",
      "location": "West End",
      "start_date": "2025-12-02",
      "start_time": "08:00",
      "available_spot_count": 16,
      "capacity": 17
    },
    {
      "studio": "Ritual",
      "name": "Vinyasa Slow Flow Yoga + Sound",
      "booking_start_date": "2025-11-25 08:00",
      "location": "West End",
      "start_date": "2025-12-09",
      "start_time": "08:00",
      "available_spot_count": 17,
      "capacity": 17
    },
    {
      "studio": "Ritual",
      "name": "Vinyasa Slow Flow Yoga + Sound",
      "booking_start_date": "2025-12-02 08:00",
      "location": "West End",
      "start_date": "2025-12-16",
      "start_time": "08:00",
      "available_spot_count": 17,
      "capacity": 17
    },
    {
      "studio": "Ritual",
      "name": "Vinyasa Slow Flow Yoga + Sound",
      "booking_start_date": "2025-12-09 08:00",
      "location": "West End",
      "start_date": "2025-12-23",
      "start_time": "08:00",
      "available_spot_count": 17,
      "capacity": 17
    },
    {
      "studio": "Ritual",
      "name": "Vinyasa Slow Flow Yoga + Sound",
      "booking_start_date": "2025-12-16 08:00",
      "location": "West End",
      "start_date": "2025-12-30",
      "start_time": "08:00",
      "available_spot_count": 17,
      "capacity": 17
    },
    {
      "studio": "Ritual",
      "name": "Vinyasa Slow Flow Yoga + Sound",
      "booking_start_date": "2025-12-23 08:00",
      "location": "West End",
      "start_date": "2026-01-06",
      "start_time": "08:00",
      "available_spot_count": 17,
      "capacity": 17
    },
    {
      "studio": "Spin Society",
      "name": "THEME: BUNT x Fred Again...",
      "booking_start_date": "2025-11-20 12:00",
      "location": "MOUNT PLEASANT",
      "start_date": "2025-11-28",
      "start_time": "12:30",
      "available_spot_count": 18,
      "capacity": 45
    },
    {
      "studio": "Spin Society",
      "name": "THEME: Latin Beats x EDM",
      "booking_start_date": "2025-11-20 12:00",
      "location": "MOUNT PLEASANT",
      "start_date": "2025-11-28",
      "start_time": "15:00",
      "available_spot_count": 30,
      "capacity": 45
    },
    {
      "studio": "Spin Society",
      "name": "THEME: DISNEY STARS! Jonas Bros x Hilary x Demi",
      "booking_start_date": "2025-11-20 12:00",
      "location": "MOUNT PLEASANT",
      "start_date": "2025-11-28",
      "start_time": "18:40",
      "available_spot_count": 1,
      "capacity": 45
    },
    {
      "studio": "Spin Society",
      "name": "THEME: VEGAS | DJs + Residencies",
      "booking_start_date": "2025-11-22 12:00",
      "location": "MOUNT PLEASANT",
      "start_date": "2025-11-30",
      "start_time": "10:40",
      "available_spot_count": 0,
      "capacity": 45
    },
    {
      "studio": "Spin Society",
      "name": "THEME: MILLENNIAL MONDAY: POP X HIP HOP",
      "booking_start_date": "2025-11-23 12:00",
      "location": "MOUNT PLEASANT",
      "start_date": "2025-12-01",
      "start_time": "09:45",
      "available_spot_count": 24,
      "capacity": 45
    },
    {
      "studio": "Spin Society",
      "name": "THEME: COUNTRY x POP",
      "booking_start_date": "2025-11-23 12:00",
      "location": "MOUNT PLEASANT",
      "start_date": "2025-12-01",
      "start_time": "18:40",
      "available_spot_count": 0,
      "capacity": 45
    },
    {
      "studio": "Spin Society",
      "name": "THEME: EDM: GRITTY x OBNOXIOUS - VOL 2",
      "booking_start_date": "2025-11-24 12:00",
      "location": "MOUNT PLEASANT",
      "start_date": "2025-12-02",
      "start_time": "11:00",
      "available_spot_count": 24,
      "capacity": 45
    },
    {
      "studio": "Spin Society",
      "name": "THEME: Dancing With The Stars",
      "booking_start_date": "2025-11-24 12:00",
      "location": "MOUNT PLEASANT",
      "start_date": "2025-12-02",
      "start_time": "17:30",
      "available_spot_count": 18,
      "capacity": 45
    },
    {
      "studio": "Spin Society",
      "name": "THEME: Taylor Swift: Rep x TLOASG",
      "booking_start_date": "2025-11-25 12:00",
      "location": "MOUNT PLEASANT",
      "start_date": "2025-12-03",
      "start_time": "06:00",
      "available_spot_count": 24,
      "capacity": 45
    },
    {
      "studio": "Spin Society",
      "name": "THEME: Doechii x SZA x Doja Cat",
      "booking_start_date": "2025-11-26 12:00",
      "location": "MOUNT PLEASANT",
      "start_date": "2025-12-04",
      "start_time": "09:45",
      "available_spot_count": 35,
      "capacity": 45
    },
    {
      "studio": "Spin Society",
      "name": "THEME: Sweedish House Mafia x Lady Gaga",
      "booking_start_date": "2025-11-27 12:00",
      "location": "MOUNT PLEASANT",
      "start_date": "2025-12-05",
      "start_time": "12:30",
      "available_spot_count": 38,
      "capacity": 45
    },
    {
      "studio": "Spin Society",
      "name": "THEME: Hannah Montana x The Cheetah Girls",
      "booking_start_date": "2025-11-30 12:00",
      "location": "MOUNT PLEASANT",
      "start_date": "2025-12-08",
      "start_time": "07:15",
      "available_spot_count": 45,
      "capacity": 45
    },
    {
      "studio": "Spin Society",
      "name": "THEME: Extreme EDM",
      "booking_start_date": "2025-11-30 12:00",
      "location": "MOUNT PLEASANT",
      "start_date": "2025-12-08",
      "start_time": "16:20",
      "available_spot_count": 45,
      "capacity": 45
    },
    {
      "studio": "Spin Society",
      "name": "THEME: Remixed Pop Hits",
      "booking_start_date": "2025-12-01 12:00",
      "location": "MOUNT PLEASANT",
      "start_date": "2025-12-09",
      "start_time": "12:30",
      "available_spot_count": 45,
      "capacity": 45
    },
    {
      "studio": "Spin Society",
      "name": "THEME: Tate McRae x Zara Larsson",
      "booking_start_date": "2025-12-01 12:00",
      "location": "MOUNT PLEASANT",
      "start_date": "2025-12-09",
      "start_time": "17:30",
      "available_spot_count": 45,
      "capacity": 45
    },
    {
      "studio": "Spin Society",
      "name": "THEME: THEME: Hannah Montana x The Cheetah Girls",
      "booking_start_date": "2025-12-02 12:00",
      "location": "MOUNT PLEASANT",
      "start_date": "2025-12-10",
      "start_time": "12:30",
      "available_spot_count": 50,
      "capacity": 50
    },
    {
      "studio": "Spin Society",
      "name": "THEME: ATEEZ x MONSTA X",
      "booking_start_date": "2025-12-06 12:00",
      "location": "MOUNT PLEASANT",
      "start_date": "2025-12-14",
      "start_time": "11:50",
      "available_spot_count": 50,
      "capacity": 50
    },
    {
      "studio": "Evolution",
      "name": "Infrared Lagree - DUA LIPA X ARIANA GRANDE",
      "booking_start_date": "2025-11-28 07:45",
      "location": "Vancouver",
      "start_date": "2025-12-12",
      "start_time": "07:45",
      "available_spot_count": 10,
      "capacity": 10
    },
    {
      "studio": "Evolution",
      "name": "Infrared Lagree - DUA LIPA X ARIANA GRANDE",
      "booking_start_date": "2025-11-28 08:45",
      "location": "Vancouver",
      "start_date": "2025-12-12",
      "start_time": "08:45",
      "available_spot_count": 10,
      "capacity": 10
    }
  ]
}