{
  "last_updated": "2026-01-03T14:19:55.819184-08:00",
  "special": [
    {
      "studio": "Turf",
      "name": "COMMUNITY CLASS: meta",
      "booking_start_date": "2026-01-01 08:15",
      "location": "KITS - Vancouver",
      "start_date": "2026-01-08",
      "start_time": "08:15",
      "available_spot_count": 24,
      "capacity": 32
    },
    {
      "studio": "Turf",
      "name": "COMMUNITY CLASS: meta",
      "booking_start_date": "2026-01-08 08:15",
      "location": "KITS - Vancouver",
      "start_date": "2026-01-15",
      "start_time": "08:15",
      "available_spot_count": 32,
      "capacity": 32
    },
    {
      "studio": "Turf",
      "name": "COMMUNITY CLASS: meta",
      "booking_start_date": "2026-01-15 08:15",
      "location": "KITS - Vancouver",
      "start_date": "2026-01-22",
      "start_time": "08:15",
      "available_spot_count": 32,
      "capacity": 32
    },
    {
      "studio": "Turf",
      "name": "COMMUNITY CLASS: meta",
      "booking_start_date": "2026-01-22 08:15",
      "location": "KITS - Vancouver",
      "start_date": "2026-01-29",
      "start_time": "08:15",
      "available_spot_count": 32,
      "capacity": 32
    },
    {
      "studio": "Turf",
      "name": "COMMUNITY CLASS: meta",
      "booking_start_date": "2026-01-29 08:15",
      "location": "KITS - Vancouver",
      "start_date": "2026-02-05",
      "start_time": "08:15",
      "available_spot_count": 32,
      "capacity": 32
    },
    {
      "studio": "Turf",
      "name": "COMMUNITY CLASS: meta",
      "booking_start_date": "2026-02-05 08:15",
      "location": "KITS - Vancouver",
      "start_date": "2026-02-12",
      "start_time": "08:15",
      "available_spot_count": 32,
      "capacity": 32
    }
  ],
  "sponsored": [
    {
      "studio": "Lagree West",
      "name": "Happy Hour Megaformer x Atelier Elan Coffee",
      "booking_start_date": "2025-12-29 00:00",
      "location": "Kitsilano",
      "start_date": "2026-01-05",
      "start_time": "05:15",
      "available_spot_count": 13,
      "capacity": 16
    },
    {
      "studio": "Lagree West",
      "name": "Megaformer x Atelier Elan Coffee",
      "booking_start_date": "2025-12-29 00:00",
      "location": "Kitsilano",
      "start_date": "2026-01-05",
      "start_time": "06:15",
      "available_spot_count": 0,
      "capacity": 16
    },
    {
      "studio": "Lagree West",
      "name": "Megaformer x Atelier Elan Coffee",
      "booking_start_date": "2025-12-29 00:00",
      "location": "Kitsilano",
      "start_date": "2026-01-05",
      "start_time": "07:15",
      "available_spot_count": 0,
      "capacity": 16
    },
    {
      "studio": "Lagree West",
      "name": "Megaformer x Atelier Elan Coffee",
      "booking_start_date": "2025-12-29 00:00",
      "location": "Yaletown",
      "start_date": "2026-01-05",
      "start_time": "12:15",
      "available_spot_count": 10,
      "capacity": 20
    },
    {
      "studio": "Lagree West",
      "name": "Happy Hour Megaformer x Atelier Elan Coffee",
      "booking_start_date": "2025-12-29 00:00",
      "location": "Yaletown",
      "start_date": "2026-01-05",
      "start_time": "13:15",
      "available_spot_count": 12,
      "capacity": 20
    },
    {
      "studio": "Lagree West",
      "name": "Happy Hour Megaformer x Atelier Elan Coffee",
      "booking_start_date": "2025-12-29 00:00",
      "location": "Yaletown",
      "start_date": "2026-01-05",
      "start_time": "14:15",
      "available_spot_count": 12,
      "capacity": 20
    },
    {
      "studio": "Lagree West",
      "name": "Happy Hour Megaformer x Atelier Elan Coffee",
      "booking_start_date": "2025-12-30 00:00",
      "location": "Kitsilano",
      "start_date": "2026-01-06",
      "start_time": "05:15",
      "available_spot_count": 9,
      "capacity": 16
    },
    {
      "studio": "Lagree West",
      "name": "Megaformer x Atelier Elan Coffee",
      "booking_start_date": "2025-12-30 00:00",
      "location": "Kitsilano",
      "start_date": "2026-01-06",
      "start_time": "07:15",
      "available_spot_count": 0,
      "capacity": 16
    },
    {
      "studio": "Lagree West",
      "name": "Megaformer x Atelier Elan Coffee",
      "booking_start_date": "2025-12-30 00:00",
      "location": "Yaletown",
      "start_date": "2026-01-06",
      "start_time": "12:15",
      "available_spot_count": 12,
      "capacity": 20
    },
    {
      "studio": "Lagree West",
      "name": "Happy Hour Megaformer x Atelier Elan Coffee",
      "booking_start_date": "2025-12-30 00:00",
      "location": "Yaletown",
      "start_date": "2026-01-06",
      "start_time": "13:15",
      "available_spot_count": 11,
      "capacity": 20
    },
    {
      "studio": "Lagree West",
      "name": "Happy Hour Megaformer x Atelier Elan Coffee",
      "booking_start_date": "2025-12-30 00:00",
      "location": "Yaletown",
      "start_date": "2026-01-06",
      "start_time": "14:15",
      "available_spot_count": 15,
      "capacity": 20
    },
    {
      "studio": "Lagree West",
      "name": "Megaformer x Atelier Elan Coffee",
      "booking_start_date": "2025-12-31 00:00",
      "location": "Kitsilano",
      "start_date": "2026-01-07",
      "start_time": "05:15",
      "available_spot_count": 9,
      "capacity": 16
    },
    {
      "studio": "Lagree West",
      "name": "Megaformer x Atelier Elan Coffee",
      "booking_start_date": "2025-12-31 00:00",
      "location": "Kitsilano",
      "start_date": "2026-01-07",
      "start_time": "06:15",
      "available_spot_count": 0,
      "capacity": 16
    },
    {
      "studio": "Lagree West",
      "name": "Megaformer x Atelier Elan Coffee",
      "booking_start_date": "2025-12-31 00:00",
      "location": "Yaletown",
      "start_date": "2026-01-07",
      "start_time": "12:15",
      "available_spot_count": 16,
      "capacity": 20
    },
    {
      "studio": "Lagree West",
      "name": "Happy Hour Megaformer x Atelier Elan Coffee",
      "booking_start_date": "2025-12-31 00:00",
      "location": "Yaletown",
      "start_date": "2026-01-07",
      "start_time": "13:15",
      "available_spot_count": 13,
      "capacity": 20
    },
    {
      "studio": "Lagree West",
      "name": "Happy Hour Megaformer x Atelier Elan Coffee",
      "booking_start_date": "2025-12-31 00:00",
      "location": "Yaletown",
      "start_date": "2026-01-07",
      "start_time": "14:15",
      "available_spot_count": 14,
      "capacity": 20
    },
    {
      "studio": "Lagree West",
      "name": "Happy Hour Megaformer x Atelier Elan Coffee",
      "booking_start_date": "2026-01-01 00:00",
      "location": "Kitsilano",
      "start_date": "2026-01-08",
      "start_time": "05:15",
      "available_spot_count": 11,
      "capacity": 16
    },
    {
      "studio": "Lagree West",
      "name": "Happy Hour Megaformer x Atelier Elan Coffee",
      "booking_start_date": "2026-01-01 00:00",
      "location": "Kitsilano",
      "start_date": "2026-01-08",
      "start_time": "06:15",
      "available_spot_count": 0,
      "capacity": 16
    },
    {
      "studio": "Lagree West",
      "name": "Megaformer x Atelier Elan Coffee",
      "booking_start_date": "2026-01-01 00:00",
      "location": "Kitsilano",
      "start_date": "2026-01-08",
      "start_time": "07:15",
      "available_spot_count": 4,
      "capacity": 16
    },
    {
      "studio": "Lagree West",
      "name": "Megaformer x Atelier Elan Coffee",
      "booking_start_date": "2026-01-01 00:00",
      "location": "Yaletown",
      "start_date": "2026-01-08",
      "start_time": "12:15",
      "available_spot_count": 16,
      "capacity": 20
    },
    {
      "studio": "Lagree West",
      "name": "Happy Hour Megaformer x Atelier Elan Coffee",
      "booking_start_date": "2026-01-01 00:00",
      "location": "Yaletown",
      "start_date": "2026-01-08",
      "start_time": "13:15",
      "available_spot_count": 12,
      "capacity": 20
    },
    {
      "studio": "Lagree West",
      "name": "Happy Hour Megaformer x Atelier Elan Coffee",
      "booking_start_date": "2026-01-01 00:00",
      "location": "Yaletown",
      "start_date": "2026-01-08",
      "start_time": "14:15",
      "available_spot_count": 18,
      "capacity": 20
    },
    {
      "studio": "Lagree West",
      "name": "Sweat for a Cause/By Donation",
      "booking_start_date": "2025-12-09 15:15",
      "location": "Kitsilano",
      "start_date": "2026-01-08",
      "start_time": "15:15",
      "available_spot_count": 0,
      "capacity": 16
    },
    {
      "studio": "Lagree West",
      "name": "Happy Hour Megaformer x Atelier Elan Coffee",
      "booking_start_date": "2026-01-02 00:00",
      "location": "Kitsilano",
      "start_date": "2026-01-09",
      "start_time": "05:15",
      "available_spot_count": 11,
      "capacity": 16
    },
    {
      "studio": "Lagree West",
      "name": "Happy Hour Megaformer x Atelier Elan Coffee",
      "booking_start_date": "2026-01-02 00:00",
      "location": "Kitsilano",
      "start_date": "2026-01-09",
      "start_time": "06:15",
      "available_spot_count": 2,
      "capacity": 16
    },
    {
      "studio": "Lagree West",
      "name": "Megaformer x Atelier Elan Coffee",
      "booking_start_date": "2026-01-02 00:00",
      "location": "Yaletown",
      "start_date": "2026-01-09",
      "start_time": "12:15",
      "available_spot_count": 10,
      "capacity": 20
    },
    {
      "studio": "Lagree West",
      "name": "Happy Hour Megaformer x Atelier Elan Coffee",
      "booking_start_date": "2026-01-02 00:00",
      "location": "Yaletown",
      "start_date": "2026-01-09",
      "start_time": "13:15",
      "available_spot_count": 9,
      "capacity": 20
    },
    {
      "studio": "Lagree West",
      "name": "Happy Hour Megaformer x Atelier Elan Coffee",
      "booking_start_date": "2026-01-02 00:00",
      "location": "Yaletown",
      "start_date": "2026-01-09",
      "start_time": "14:15",
      "available_spot_count": 12,
      "capacity": 20
    },
    {
      "studio": "Lagree West",
      "name": "Megaformer x Atelier Elan Coffee",
      "booking_start_date": "2026-01-03 00:00",
      "location": "Kitsilano",
      "start_date": "2026-01-10",
      "start_time": "07:00",
      "available_spot_count": 11,
      "capacity": 16
    },
    {
      "studio": "Lagree West",
      "name": "Megaformer x Atelier Elan Coffee",
      "booking_start_date": "2026-01-03 00:00",
      "location": "Kitsilano",
      "start_date": "2026-01-10",
      "start_time": "08:00",
      "available_spot_count": 2,
      "capacity": 16
    },
    {
      "studio": "Lagree West",
      "name": "Megaformer x Atelier Elan Coffee",
      "booking_start_date": "2026-01-04 00:00",
      "location": "Kitsilano",
      "start_date": "2026-01-11",
      "start_time": "07:00",
      "available_spot_count": 14,
      "capacity": 16
    },
    {
      "studio": "Lagree West",
      "name": "Megaformer x Atelier Elan Coffee",
      "booking_start_date": "2026-01-04 00:00",
      "location": "Kitsilano",
      "start_date": "2026-01-11",
      "start_time": "08:00",
      "available_spot_count": 11,
      "capacity": 16
    },
    {
      "studio": "Lagree West",
      "name": "Sweat for a Cause/By Donation",
      "booking_start_date": "2025-12-15 15:15",
      "location": "Main St",
      "start_date": "2026-01-14",
      "start_time": "15:15",
      "available_spot_count": 0,
      "capacity": 14
    },
    {
      "studio": "Lagree West",
      "name": "Sweat for a Cause/By Donation",
      "booking_start_date": "2025-12-23 12:15",
      "location": "Yaletown",
      "start_date": "2026-01-22",
      "start_time": "12:15",
      "available_spot_count": 14,
      "capacity": 20
    },
    {
      "studio": "Lagree West",
      "name": "Team Class with Tabatha C",
      "booking_start_date": "2026-02-02 00:00",
      "location": "Gastown",
      "start_date": "2026-02-09",
      "start_time": "19:15",
      "available_spot_count": 15,
      "capacity": 15
    },
    {
      "studio": "Jaybird",
      "name": "Sweat for a Cause | By Donation | The Build",
      "booking_start_date": "2026-01-16 00:00",
      "location": "Yaletown",
      "start_date": "2026-01-23",
      "start_time": "06:00",
      "available_spot_count": 36,
      "capacity": 36
    },
    {
      "studio": "Lagree Studio",
      "name": "Daytime Deals - Full Body Workout With Headsets",
      "booking_start_date": "2025-12-29 09:00",
      "location": "Vancouver",
      "start_date": "2026-01-05",
      "start_time": "09:00",
      "available_spot_count": 9,
      "capacity": 12
    },
    {
      "studio": "Lagree Studio",
      "name": "Daytime Deals- Full Body Workout With Headsets",
      "booking_start_date": "2025-12-29 15:30",
      "location": "Vancouver",
      "start_date": "2026-01-05",
      "start_time": "15:30",
      "available_spot_count": 9,
      "capacity": 12
    },
    {
      "studio": "Ritual",
      "name": "New Year Intentions - Ritual Mini Retreat",
      "booking_start_date": "2025-12-19 14:00",
      "location": "West End",
      "start_date": "2026-01-18",
      "start_time": "14:00",
      "available_spot_count": 23,
      "capacity": 25
    },
    {
      "studio": "Spin Society",
      "name": "THEME: FRED AGAIN..X HIP HOP",
      "booking_start_date": "2025-12-28 12:00",
      "location": "MOUNT PLEASANT",
      "start_date": "2026-01-05",
      "start_time": "09:45",
      "available_spot_count": 20,
      "capacity": 50
    },
    {
      "studio": "Spin Society",
      "name": "THEME : AVICII x MARTIN GARRIX x ZEDD",
      "booking_start_date": "2025-12-29 12:00",
      "location": "MOUNT PLEASANT",
      "start_date": "2026-01-06",
      "start_time": "06:00",
      "available_spot_count": 32,
      "capacity": 50
    },
    {
      "studio": "Spin Society",
      "name": "THEME: WAKE-UP WITH GAGA x JOHN SUMMIT",
      "booking_start_date": "2025-12-30 12:00",
      "location": "MOUNT PLEASANT",
      "start_date": "2026-01-07",
      "start_time": "06:00",
      "available_spot_count": 33,
      "capacity": 50
    },
    {
      "studio": "Spin Society",
      "name": "THEME: USHER x JUSTIN BIEBER",
      "booking_start_date": "2026-01-01 12:00",
      "location": "MOUNT PLEASANT",
      "start_date": "2026-01-09",
      "start_time": "18:40",
      "available_spot_count": 0,
      "capacity": 50
    },
    {
      "studio": "Spin Society",
      "name": "THEME: ILLENIUM x SEVEN LIONS x GARRIX (Vol. 2)",
      "booking_start_date": "2026-01-03 12:00",
      "location": "MOUNT PLEASANT",
      "start_date": "2026-01-11",
      "start_time": "13:00",
      "available_spot_count": 11,
      "capacity": 50
    },
    {
      "studio": "Spin Society",
      "name": "THEME: BEST OF 2025 x 2015",
      "booking_start_date": "2026-01-05 12:00",
      "location": "MOUNT PLEASANT",
      "start_date": "2026-01-13",
      "start_time": "09:45",
      "available_spot_count": 49,
      "capacity": 50
    },
    {
      "studio": "Spin Society",
      "name": "THEME : MACKLEMORE X PITBULL X USHER",
      "booking_start_date": "2026-01-06 12:00",
      "location": "MOUNT PLEASANT",
      "start_date": "2026-01-14",
      "start_time": "16:20",
      "available_spot_count": 50,
      "capacity": 50
    },
    {
      "studio": "Spin Society",
      "name": "THEME: HIP HOP x EDM",
      "booking_start_date": "2026-01-07 12:00",
      "location": "MOUNT PLEASANT",
      "start_date": "2026-01-15",
      "start_time": "12:30",
      "available_spot_count": 50,
      "capacity": 50
    },
    {
      "studio": "Spin Society",
      "name": "THEME: JOHN SUMMIT X FRED AGAIN...",
      "booking_start_date": "2026-01-08 12:00",
      "location": "MOUNT PLEASANT",
      "start_date": "2026-01-16",
      "start_time": "12:30",
      "available_spot_count": 50,
      "capacity": 50
    },
    {
      "studio": "Evolution",
      "name": "Infrared Lagree - RIHANNA REMIX",
      "booking_start_date": "2025-12-24 09:45",
      "location": "Vancouver",
      "start_date": "2026-01-07",
      "start_time": "09:45",
      "available_spot_count": 0,
      "capacity": 10
    },
    {
      "studio": "Evolution",
      "name": "Infrared Lagree - DRAKE & FRIENDS",
      "booking_start_date": "2025-12-31 09:45",
      "location": "Vancouver",
      "start_date": "2026-01-14",
      "start_time": "09:45",
      "available_spot_count": 8,
      "capacity": 10
    },
    {
      "studio": "Evolution",
      "name": "Infrared Lagree - 2000s R&B | HIP HOP",
      "booking_start_date": "2026-01-07 09:45",
      "location": "Vancouver",
      "start_date": "2026-01-21",
      "start_time": "09:45",
      "available_spot_count": 10,
      "capacity": 10
    },
    {
      "studio": "Evolution",
      "name": "Infrared Lagree - RIHANNA ENERGY",
      "booking_start_date": "2026-01-14 09:45",
      "location": "Vancouver",
      "start_date": "2026-01-28",
      "start_time": "09:45",
      "available_spot_count": 10,
      "capacity": 10
    }
  ]
}